progshot/__init__.py
progshot/cli.py
progshot/film.py
progshot/progshot.py
progshot/psviewer.py
progshot/pswebserver.py
progshot/serverbooter.py
progshot/webinterface.py
progshot/frontend/asset-manifest.json
progshot/frontend/index.html
progshot/frontend/manifest.json
progshot/frontend/robots.txt
progshot/frontend/static/css/2.f3d8d925.chunk.css
progshot/frontend/static/css/2.f3d8d925.chunk.css.map
progshot/frontend/static/css/main.3d97d315.chunk.css
progshot/frontend/static/css/main.3d97d315.chunk.css.map
progshot/frontend/static/js/2.63213e28.chunk.js
progshot/frontend/static/js/2.63213e28.chunk.js.LICENSE.txt
progshot/frontend/static/js/2.63213e28.chunk.js.map
progshot/frontend/static/js/3.f32fb021.chunk.js
progshot/frontend/static/js/3.f32fb021.chunk.js.map
progshot/frontend/static/js/main.94783124.chunk.js
progshot/frontend/static/js/main.94783124.chunk.js.map
progshot/frontend/static/js/runtime-main.efafdd99.js
progshot/frontend/static/js/runtime-main.efafdd99.js.map
progshot-0.0.1.dist-info/LICENSE
progshot-0.0.1.dist-info/METADATA
progshot-0.0.1.dist-info/NOTICE.txt
progshot-0.0.1.dist-info/WHEEL
progshot-0.0.1.dist-info/entry_points.txt
progshot-0.0.1.dist-info/top_level.txt
progshot-0.0.1.dist-info/RECORD
