Metadata-Version: 2.1
Name: progshot
Version: 0.0.1
Summary: A debugging tool to take 'screenshot' of your program
Home-page: https://github.com/gaogaotiantian/progshot
Author: Tian Gao
Author-email: gaogaotiantian@hotmail.com
License: UNKNOWN
Platform: UNKNOWN
Classifier: Development Status :: 3 - Alpha
Classifier: Programming Language :: Python :: 3.7
Classifier: Programming Language :: Python :: 3.8
Classifier: Programming Language :: Python :: 3.9
Classifier: Intended Audience :: Developers
Classifier: License :: OSI Approved :: Apache Software License
Classifier: Operating System :: OS Independent
Requires-Python: >=3.6
Requires-Dist: dill (>=0.3.3)
Requires-Dist: rich (>=10.2.1)
Requires-Dist: objprint (>=0.1.0)
Requires-Dist: websockets (>=9.1)
